{
  "name": "Posts",
  "options": {
    "idInjection": false,
    "mysql": {
      "schema": "blog",
      "table": "posts"
    },
    "automaticValidation": false
  },
  "relations": {
    "blogs": {
      "type": "belongsTo",
      "model": "Blogs",
      "foreignKey": "blogId"
    },
    "comments": {
      "type": "hasMany",
      "model": "Comments",
      "foreignKey": "postId"
    },
    "postAccess": {
      "type": "hasMany",
      "model": "PostAccess",
      "foreignKey": "postId"
    },
    "postTags": {
      "type": "hasMany",
      "model": "PostTags",
      "foreignKey": "postId"
    }
  },
  "properties": {
    "id": {
      "type": "Number",
      "required": false,
      "length": null,
      "precision": 10,
      "scale": 0,
      "id": 1,
      "mysql": {
        "columnName": "id",
        "dataType": "int",
        "dataLength": null,
        "dataPrecision": 10,
        "dataScale": 0,
        "nullable": "N"
      }
    },
    "isValid": {
      "type": "Number",
      "required": false,
      "length": null,
      "precision": 3,
      "scale": 0,
      "mysql": {
        "columnName": "is_valid",
        "dataType": "tinyint",
        "dataLength": null,
        "dataPrecision": 3,
        "dataScale": 0,
        "nullable": "N"
      }
    },
    "isDraft": {
      "type": "Number",
      "required": false,
      "length": null,
      "precision": 3,
      "scale": 0,
      "mysql": {
        "columnName": "is_draft",
        "dataType": "tinyint",
        "dataLength": null,
        "dataPrecision": 3,
        "dataScale": 0,
        "nullable": "N"
      }
    },
    "isEnableComment": {
      "type": "Number",
      "required": false,
      "length": null,
      "precision": 3,
      "scale": 0,
      "mysql": {
        "columnName": "is_enable_comment",
        "dataType": "tinyint",
        "dataLength": null,
        "dataPrecision": 3,
        "dataScale": 0,
        "nullable": "N"
      }
    },
    "publishedAt": {
      "type": "Date",
      "required": false,
      "length": null,
      "precision": null,
      "scale": null,
      "mysql": {
        "columnName": "published_at",
        "dataType": "timestamp",
        "dataLength": null,
        "dataPrecision": null,
        "dataScale": null,
        "nullable": "Y"
      }
    },
    "blogId": {
      "type": "Number",
      "required": false,
      "length": null,
      "precision": 10,
      "scale": 0,
      "mysql": {
        "columnName": "blog_id",
        "dataType": "int",
        "dataLength": null,
        "dataPrecision": 10,
        "dataScale": 0,
        "nullable": "N"
      }
    },
    "imageNumbers": {
      "type": "String",
      "required": false,
      "length": 255,
      "precision": null,
      "scale": null,
      "mysql": {
        "columnName": "image_numbers",
        "dataType": "varchar",
        "dataLength": 255,
        "dataPrecision": null,
        "dataScale": null,
        "nullable": "Y"
      }
    },
    "headImageUrl": {
      "type": "String",
      "required": false,
      "length": 255,
      "precision": null,
      "scale": null,
      "mysql": {
        "columnName": "head_image_url",
        "dataType": "varchar",
        "dataLength": 255,
        "dataPrecision": null,
        "dataScale": null,
        "nullable": "Y"
      }
    },
    "title": {
      "type": "String",
      "required": false,
      "length": 255,
      "precision": null,
      "scale": null,
      "mysql": {
        "columnName": "title",
        "dataType": "varchar",
        "dataLength": 255,
        "dataPrecision": null,
        "dataScale": null,
        "nullable": "Y"
      }
    },
    "content": {
      "type": "String",
      "required": false,
      "length": 65535,
      "precision": null,
      "scale": null,
      "mysql": {
        "columnName": "content",
        "dataType": "text",
        "dataLength": 65535,
        "dataPrecision": null,
        "dataScale": null,
        "nullable": "Y"
      }
    },
    "slug": {
      "type": "String",
      "required": false,
      "length": 255,
      "precision": null,
      "scale": null,
      "mysql": {
        "columnName": "slug",
        "dataType": "varchar",
        "dataLength": 255,
        "dataPrecision": null,
        "dataScale": null,
        "nullable": "Y"
      }
    },
    "accessCount": {
      "type": "Number",
      "required": false,
      "length": null,
      "precision": 10,
      "scale": 0,
      "mysql": {
        "columnName": "access_count",
        "dataType": "int",
        "dataLength": null,
        "dataPrecision": 10,
        "dataScale": 0,
        "nullable": "N"
      }
    },
    "accessCountDaily": {
      "type": "Number",
      "required": true,
      "length": null,
      "precision": 10,
      "scale": 0,
      "mysql": {
        "columnName": "access_count_daily",
        "dataType": "int",
        "dataLength": null,
        "dataPrecision": 10,
        "dataScale": 0,
        "nullable": "N"
      }
    },
    "accessCountWeekly": {
      "type": "Number",
      "required": true,
      "length": null,
      "precision": 10,
      "scale": 0,
      "mysql": {
        "columnName": "access_count_weekly",
        "dataType": "int",
        "dataLength": null,
        "dataPrecision": 10,
        "dataScale": 0,
        "nullable": "N"
      }
    },
    "accessCountMonthly": {
      "type": "Number",
      "required": true,
      "length": null,
      "precision": 10,
      "scale": 0,
      "mysql": {
        "columnName": "access_count_monthly",
        "dataType": "int",
        "dataLength": null,
        "dataPrecision": 10,
        "dataScale": 0,
        "nullable": "N"
      }
    },
    "createdAt": {
      "type": "Date",
      "required": false,
      "length": null,
      "precision": null,
      "scale": null,
      "mysql": {
        "columnName": "created_at",
        "dataType": "timestamp",
        "dataLength": null,
        "dataPrecision": null,
        "dataScale": null,
        "nullable": "N"
      }
    },
    "updatedAt": {
      "type": "Date",
      "required": false,
      "length": null,
      "precision": null,
      "scale": null,
      "mysql": {
        "columnName": "updated_at",
        "dataType": "timestamp",
        "dataLength": null,
        "dataPrecision": null,
        "dataScale": null,
        "nullable": "N"
      }
    }
  },
  "mixins": {
    "UnixTimestamp": true,
    "Query": true
  }
}
